dategen/__init__.py
dategen/dategen.py
dategen-1.0.2.dist-info/LICENSE
dategen-1.0.2.dist-info/WHEEL
dategen-1.0.2.dist-info/METADATA
dategen-1.0.2.dist-info/RECORD
