Metadata-Version: 2.1
Name: dategen
Version: 1.0.2
Summary: A date generator.
Home-page: https://codeberg.org/cmc/dategen
Author: Chang-Ming Chen
Author-email: changming.chen.1970@gmail.com
Classifier: License :: OSI Approved :: MIT License
